mst/vault/__init__.py
mst_vault-1.2.0.dist-info/METADATA
mst_vault-1.2.0.dist-info/WHEEL
mst_vault-1.2.0.dist-info/top_level.txt
mst_vault-1.2.0.dist-info/RECORD
