Metadata-Version: 2.4
Name: mst-vault
Version: 1.2.0
Summary: Module to access the S&T IT Vault server
Author-email: Missouri University of Science and Technology - Information Technology <it-ai@mst.edu>
Requires-Python: >=3.8
Requires-Dist: mst-core
Requires-Dist: hvac
